openpython/__init__.py
openpython/__main__.py
openpython/pkgs/__init__.py
openpython/pkgs/better_logs.py
openpython/pkgs/fastapify.py
openpython/pkgs/licenses.py
openpython/pkgs/scraper.py
openpy_pkg-1.3.2.dist-info/LICENSE
openpy_pkg-1.3.2.dist-info/METADATA
openpy_pkg-1.3.2.dist-info/WHEEL
openpy_pkg-1.3.2.dist-info/top_level.txt
openpy_pkg-1.3.2.dist-info/RECORD
