Metadata-Version: 2.1
Name: openpy-pkg
Version: 1.3.2
Summary: OpenPython is a python package that allows users to collaborate to make the best python package available!
Home-page: https://github.com/thatcodingdonut/openpython
Author: Corbin Chandler
Author-email: corbinchandler777@icloud.com
Classifier: Programming Language :: Python :: 3
Classifier: License :: OSI Approved :: MIT License
Classifier: Operating System :: OS Independent
Requires-Python: >=3.6
License-File: LICENSE
Requires-Dist: colorama
Requires-Dist: matplotlib
Requires-Dist: bs4
